{
  "generatedAt": "2026-07-14T21:46:03.449860+00:00",
  "plugins": [
    {
      "aiDevelopment": "primary",
      "description": "Draw subtle elbow connectors from parent bullets to their children.",
      "id": "page.tine.bullet-threading",
      "license": "MIT",
      "name": "Bullet threading",
      "source": "https://github.com/martinkoutecky/tine-plugin-bullet-threading",
      "versions": [
        {
          "apiVersion": "0.1",
          "audit": {
            "automatedDisposition": "publish",
            "checkedAt": "2026-07-11T06:28:43.462Z",
            "manualApproval": false,
            "risk": "low",
            "sha256": "86ed64a76cd67881c85fe7955758b5c23667f353aed970ebb126c35892b203be",
            "status": "passed",
            "url": "https://raw.githubusercontent.com/martinkoutecky/tine-plugin-registry/main/audits/page.tine.bullet-threading/0.1.0.json"
          },
          "capabilities": [
            "block-decorations.register"
          ],
          "manifestSha256": "33d7f136741994465f5b7a58e9be679caa9e9f623f4083e2404cd81a332f6cea",
          "manifestUrl": "https://raw.githubusercontent.com/martinkoutecky/tine-plugin-registry/main/packages/page.tine.bullet-threading/0.1.0/manifest.json",
          "platforms": [
            "desktop",
            "android",
            "ios"
          ],
          "publishedAt": "2026-07-11T06:33:23.720650+00:00",
          "sha256": "781889abcb030f058da5fadf25eb157af7e8e16fe1826df817f762517fa2b694",
          "version": "0.1.0",
          "wasmUrl": "https://raw.githubusercontent.com/martinkoutecky/tine-plugin-registry/main/packages/page.tine.bullet-threading/0.1.0/plugin.wasm"
        },
        {
          "apiVersion": "0.2",
          "audit": {
            "automatedDisposition": "publish",
            "checkedAt": "2026-07-12T22:34:31.886Z",
            "manualApproval": false,
            "risk": "low",
            "sha256": "a9c056189452884c4768a074c4a3a1bdd8d89c0c814ea6ad2e91fd9effac034d",
            "status": "passed",
            "url": "https://raw.githubusercontent.com/martinkoutecky/tine-plugin-registry/main/audits/page.tine.bullet-threading/0.2.0.json"
          },
          "capabilities": [
            "block-decorations.register",
            "settings.read"
          ],
          "manifestSha256": "f3d7857537faeeddeb7af74c497b90bd532a2b8df02ead670b42a83c09870619",
          "manifestUrl": "https://raw.githubusercontent.com/martinkoutecky/tine-plugin-registry/main/packages/page.tine.bullet-threading/0.2.0/manifest.json",
          "platforms": [
            "desktop",
            "android",
            "ios"
          ],
          "publishedAt": "2026-07-12T22:42:34.084036+00:00",
          "sha256": "ef39dbfa30c2703b564d0456b043c363c0efd4340a690a1397b1cd229d01beaa",
          "version": "0.2.0",
          "wasmUrl": "https://raw.githubusercontent.com/martinkoutecky/tine-plugin-registry/main/packages/page.tine.bullet-threading/0.2.0/plugin.wasm"
        }
      ]
    },
    {
      "aiDevelopment": "primary",
      "description": "Set or clear the focused block's heading level with remappable commands and shortcuts.",
      "id": "page.tine.heading-level-shortcuts",
      "license": "MIT",
      "name": "Heading level shortcuts",
      "source": "https://github.com/martinkoutecky/tine-plugin-heading-level-shortcuts",
      "versions": [
        {
          "apiVersion": "0.2",
          "audit": {
            "automatedDisposition": "quarantine",
            "checkedAt": "2026-07-12T22:41:56.649Z",
            "manualApproval": true,
            "risk": "review",
            "sha256": "adb728bd46628a09898a35a08688188c77c299ae04fb7eef94a5d94124529af0",
            "status": "passed",
            "url": "https://raw.githubusercontent.com/martinkoutecky/tine-plugin-registry/main/audits/page.tine.heading-level-shortcuts/0.1.0.json"
          },
          "capabilities": [
            "commands.register",
            "graph.write.block"
          ],
          "manifestSha256": "33b793be84fdc35f9e5995dad966ccb3cf7734e6b92bac8ac3b283abe48529ab",
          "manifestUrl": "https://raw.githubusercontent.com/martinkoutecky/tine-plugin-registry/main/packages/page.tine.heading-level-shortcuts/0.1.0/manifest.json",
          "platforms": [
            "desktop",
            "android",
            "ios"
          ],
          "publishedAt": "2026-07-12T22:42:34.134923+00:00",
          "sha256": "d7235e883376f8e0ad6a4466f3058d8552ab756d250a66d27afbd15b191a859e",
          "version": "0.1.0",
          "wasmUrl": "https://raw.githubusercontent.com/martinkoutecky/tine-plugin-registry/main/packages/page.tine.heading-level-shortcuts/0.1.0/plugin.wasm"
        }
      ]
    },
    {
      "aiDevelopment": "primary",
      "description": "Add a hide-completed formula filter to the focused query table or board.",
      "id": "page.tine.query-filter",
      "license": "MIT",
      "name": "Query filter shortcuts",
      "source": "https://github.com/martinkoutecky/tine-plugin-query-filter",
      "versions": [
        {
          "apiVersion": "0.1",
          "audit": {
            "automatedDisposition": "quarantine",
            "checkedAt": "2026-07-11T06:32:06.943Z",
            "manualApproval": true,
            "risk": "review",
            "sha256": "11286ef02352c5a3690ac8c4452c46b989d53d8dda81a9a7411c391ff4fb4e6e",
            "status": "passed",
            "url": "https://raw.githubusercontent.com/martinkoutecky/tine-plugin-registry/main/audits/page.tine.query-filter/0.1.0.json"
          },
          "capabilities": [
            "commands.register",
            "graph.write.block"
          ],
          "manifestSha256": "4dfbee7758f463ba32b2d82b0859f2019344f2a0886c9447e17abea3aa0c4b40",
          "manifestUrl": "https://raw.githubusercontent.com/martinkoutecky/tine-plugin-registry/main/packages/page.tine.query-filter/0.1.0/manifest.json",
          "platforms": [
            "desktop",
            "android",
            "ios"
          ],
          "publishedAt": "2026-07-11T06:33:54.848244+00:00",
          "sha256": "b4c73358abe5535fc450f02b0b445f607294044cf0c9c470b740f120b2a93626",
          "version": "0.1.0",
          "wasmUrl": "https://raw.githubusercontent.com/martinkoutecky/tine-plugin-registry/main/packages/page.tine.query-filter/0.1.0/plugin.wasm"
        },
        {
          "apiVersion": "0.1",
          "audit": {
            "automatedDisposition": "quarantine",
            "checkedAt": "2026-07-11T16:47:26.780Z",
            "manualApproval": true,
            "risk": "review",
            "sha256": "e9af5a8f472a0d0fe39a9a3edfde98380e4bbcd9cd50e45bc6e524837b8210d3",
            "status": "passed",
            "url": "https://raw.githubusercontent.com/martinkoutecky/tine-plugin-registry/main/audits/page.tine.query-filter/0.1.1.json"
          },
          "capabilities": [
            "commands.register",
            "graph.write.block"
          ],
          "manifestSha256": "51d00252157730caacc00d05a5c24f17529fe95cd5139b7b2758427e9bdc1612",
          "manifestUrl": "https://raw.githubusercontent.com/martinkoutecky/tine-plugin-registry/main/packages/page.tine.query-filter/0.1.1/manifest.json",
          "platforms": [
            "desktop",
            "android",
            "ios"
          ],
          "publishedAt": "2026-07-11T16:48:49.229434+00:00",
          "sha256": "9412539304763c8b2e0bff76f4c656b8a28c064bdaf942bf0177bfc1a0e5282b",
          "version": "0.1.1",
          "wasmUrl": "https://raw.githubusercontent.com/martinkoutecky/tine-plugin-registry/main/packages/page.tine.query-filter/0.1.1/plugin.wasm"
        },
        {
          "apiVersion": "0.2",
          "audit": {
            "automatedDisposition": "quarantine",
            "checkedAt": "2026-07-12T22:38:08.549Z",
            "manualApproval": true,
            "risk": "review",
            "sha256": "4b3a388d02b241bc9cad530039c0f61d58feb3b19778ab92c24a6fe84f5b6a8d",
            "status": "passed",
            "url": "https://raw.githubusercontent.com/martinkoutecky/tine-plugin-registry/main/audits/page.tine.query-filter/0.2.0.json"
          },
          "capabilities": [
            "commands.register",
            "graph.write.block"
          ],
          "manifestSha256": "68bb6f639c623c082ebd587baa8f10c734ef7c3d5d840a3a1799fb2c7f481ee0",
          "manifestUrl": "https://raw.githubusercontent.com/martinkoutecky/tine-plugin-registry/main/packages/page.tine.query-filter/0.2.0/manifest.json",
          "platforms": [
            "desktop",
            "android",
            "ios"
          ],
          "publishedAt": "2026-07-12T22:42:34.126708+00:00",
          "sha256": "187423b0bee124ae2386516967c3eb7e349cba614c5dfd7185459255092ce63c",
          "version": "0.2.0",
          "wasmUrl": "https://raw.githubusercontent.com/martinkoutecky/tine-plugin-registry/main/packages/page.tine.query-filter/0.2.0/plugin.wasm"
        }
      ]
    }
  ],
  "revocations": [],
  "schemaVersion": 1,
  "themes": [
    {
      "aiDevelopment": "primary",
      "description": "A color-only Tine port of Logseq Dev Theme's light and dark palettes. Fonts, layout, and bullet-threading CSS are intentionally excluded.",
      "id": "org.tine.theme.dev",
      "license": "MIT",
      "name": "Dev Theme Colors",
      "source": "https://github.com/martinkoutecky/tine-theme-dev",
      "versions": [
        {
          "apiVersion": "0.1",
          "audit": {
            "automatedDisposition": "publish",
            "checkedAt": "2026-07-12T22:03:42.052Z",
            "manualApproval": false,
            "risk": "low",
            "sha256": "5258147de2293551d62e7ee40ccb598ca7cc37405992e0533ffb07f8dfaa1be1",
            "status": "passed",
            "url": "https://raw.githubusercontent.com/martinkoutecky/tine-plugin-registry/main/audits/org.tine.theme.dev/1.0.0.json"
          },
          "manifestSha256": "545759725b2ba1f304526f08ba61b80adb4d198df669bf1099edc8268d1b3074",
          "manifestUrl": "https://raw.githubusercontent.com/martinkoutecky/tine-plugin-registry/main/themes/org.tine.theme.dev/1.0.0/theme.json",
          "modes": [
            "dark",
            "light"
          ],
          "publishedAt": "2026-07-12T22:06:25.249316+00:00",
          "version": "1.0.0"
        },
        {
          "apiVersion": "0.1",
          "audit": {
            "automatedDisposition": "publish",
            "checkedAt": "2026-07-13T17:18:48.303Z",
            "manualApproval": false,
            "risk": "low",
            "sha256": "1b59f0863a41e7a40242fbedaf81467248a7453452796e98b1d682a473f4b01d",
            "status": "passed",
            "url": "https://raw.githubusercontent.com/martinkoutecky/tine-plugin-registry/main/audits/org.tine.theme.dev/1.0.1.json"
          },
          "manifestSha256": "172a6b710462191c334bafb94d3b111055842c68823efe94202cb3cb660aae7c",
          "manifestUrl": "https://raw.githubusercontent.com/martinkoutecky/tine-plugin-registry/main/themes/org.tine.theme.dev/1.0.1/theme.json",
          "modes": [
            "dark",
            "light"
          ],
          "publishedAt": "2026-07-14T21:46:01.517754+00:00",
          "version": "1.0.1"
        }
      ]
    },
    {
      "aiDevelopment": "primary",
      "description": "A color-only Tine port of the Obsidian Things theme. Layout, fonts, icons, checkbox styling, and plugin-specific CSS are intentionally excluded.",
      "id": "org.tine.theme.things",
      "license": "MIT",
      "name": "Things Colors",
      "source": "https://github.com/martinkoutecky/tine-theme-things",
      "versions": [
        {
          "apiVersion": "0.1",
          "audit": {
            "automatedDisposition": "publish",
            "checkedAt": "2026-07-12T22:04:35.704Z",
            "manualApproval": false,
            "risk": "low",
            "sha256": "dc2cfda217014044ffb0ccd7d579a059025f08fd05b02007908bfe718719f3f2",
            "status": "passed",
            "url": "https://raw.githubusercontent.com/martinkoutecky/tine-plugin-registry/main/audits/org.tine.theme.things/1.0.0.json"
          },
          "manifestSha256": "b2df2c2cb8809e708ff7b9d8403ca76d34bc6d22f229823578ab08e926177bb1",
          "manifestUrl": "https://raw.githubusercontent.com/martinkoutecky/tine-plugin-registry/main/themes/org.tine.theme.things/1.0.0/theme.json",
          "modes": [
            "dark",
            "light"
          ],
          "publishedAt": "2026-07-12T22:06:25.257307+00:00",
          "version": "1.0.0"
        },
        {
          "apiVersion": "0.1",
          "audit": {
            "automatedDisposition": "publish",
            "checkedAt": "2026-07-13T17:18:48.340Z",
            "manualApproval": false,
            "risk": "low",
            "sha256": "02406bf8c7e0da0d7f61280cb17d1803f6f6ca9c0a3ea1a09b2f81f4800eef1a",
            "status": "passed",
            "url": "https://raw.githubusercontent.com/martinkoutecky/tine-plugin-registry/main/audits/org.tine.theme.things/1.0.1.json"
          },
          "manifestSha256": "c6c9a0d2b328a97cd9f28951049522c56bcc2a978b1d0243f0eae429267421ab",
          "manifestUrl": "https://raw.githubusercontent.com/martinkoutecky/tine-plugin-registry/main/themes/org.tine.theme.things/1.0.1/theme.json",
          "modes": [
            "dark",
            "light"
          ],
          "publishedAt": "2026-07-14T21:46:03.449844+00:00",
          "version": "1.0.1"
        }
      ]
    }
  ]
}
